{
  "_format": "hh-sol-cache-2",
  "files": {
    "/home/runner/work/base-app/base-app/contracts/Sample_2026_02_14_01_22.sol": {
      "lastModificationDate": 1771192594036,
      "contentHash": "1eae0649ad0e5d415f1c65e5f4c90323",
      "sourceName": "contracts/Sample_2026_02_14_01_22.sol",
      "solcConfig": {
        "version": "0.8.20",
        "settings": {
          "evmVersion": "paris",
          "optimizer": {
            "enabled": false,
            "runs": 200
          },
          "outputSelection": {
            "*": {
              "*": [
                "abi",
                "evm.bytecode",
                "evm.deployedBytecode",
                "evm.methodIdentifiers",
                "metadata"
              ],
              "": [
                "ast"
              ]
            }
          }
        }
      },
      "imports": [],
      "versionPragmas": [
        "^0.8.20"
      ],
      "artifacts": [
        "Sample_2026_02_14_01_22"
      ]
    },
    "/home/runner/work/base-app/base-app/contracts/Sample_2026_02_14_11_57.sol": {
      "lastModificationDate": 1771147965308,
      "contentHash": "0dd9fb7b0bd4410466e2351d97415af6",
      "sourceName": "contracts/Sample_2026_02_14_11_57.sol",
      "solcConfig": {
        "version": "0.8.20",
        "settings": {
          "evmVersion": "paris",
          "optimizer": {
            "enabled": false,
            "runs": 200
          },
          "outputSelection": {
            "*": {
              "*": [
                "abi",
                "evm.bytecode",
                "evm.deployedBytecode",
                "evm.methodIdentifiers",
                "metadata"
              ],
              "": [
                "ast"
              ]
            }
          }
        }
      },
      "imports": [],
      "versionPragmas": [
        "^0.8.20"
      ],
      "artifacts": [
        "Sample_2026_02_14_11_57"
      ]
    },
    "/home/runner/work/base-app/base-app/contracts/Sample_2026_02_14_15_48.sol": {
      "lastModificationDate": 1771273077810,
      "contentHash": "41b3ac31021d75529881110a520d21bc",
      "sourceName": "contracts/Sample_2026_02_14_15_48.sol",
      "solcConfig": {
        "version": "0.8.20",
        "settings": {
          "evmVersion": "paris",
          "optimizer": {
            "enabled": false,
            "runs": 200
          },
          "outputSelection": {
            "*": {
              "*": [
                "abi",
                "evm.bytecode",
                "evm.deployedBytecode",
                "evm.methodIdentifiers",
                "metadata"
              ],
              "": [
                "ast"
              ]
            }
          }
        }
      },
      "imports": [],
      "versionPragmas": [
        "^0.8.20"
      ],
      "artifacts": [
        "Sample_2026_02_14_15_48"
      ]
    },
    "/home/runner/work/base-app/base-app/contracts/Sample_2026_02_14_17_56.sol": {
      "lastModificationDate": 1771274977175,
      "contentHash": "2636542901f79bd351c0bf737bf54872",
      "sourceName": "contracts/Sample_2026_02_14_17_56.sol",
      "solcConfig": {
        "version": "0.8.20",
        "settings": {
          "evmVersion": "paris",
          "optimizer": {
            "enabled": false,
            "runs": 200
          },
          "outputSelection": {
            "*": {
              "*": [
                "abi",
                "evm.bytecode",
                "evm.deployedBytecode",
                "evm.methodIdentifiers",
                "metadata"
              ],
              "": [
                "ast"
              ]
            }
          }
        }
      },
      "imports": [],
      "versionPragmas": [
        "^0.8.20"
      ],
      "artifacts": [
        "Sample_2026_02_14_17_56"
      ]
    },
    "/home/runner/work/base-app/base-app/contracts/Sample_2026_02_14_20_17.sol": {
      "lastModificationDate": 1771264204313,
      "contentHash": "a81017fb25079065a4716e07b10c127e",
      "sourceName": "contracts/Sample_2026_02_14_20_17.sol",
      "solcConfig": {
        "version": "0.8.20",
        "settings": {
          "evmVersion": "paris",
          "optimizer": {
            "enabled": false,
            "runs": 200
          },
          "outputSelection": {
            "*": {
              "*": [
                "abi",
                "evm.bytecode",
                "evm.deployedBytecode",
                "evm.methodIdentifiers",
                "metadata"
              ],
              "": [
                "ast"
              ]
            }
          }
        }
      },
      "imports": [],
      "versionPragmas": [
        "^0.8.20"
      ],
      "artifacts": [
        "Sample_2026_02_14_20_17"
      ]
    },
    "/home/runner/work/base-app/base-app/contracts/Sample_2026_02_15_06_07.sol": {
      "lastModificationDate": 1771268765061,
      "contentHash": "bedec51e1596357b0d2ba4930449b16c",
      "sourceName": "contracts/Sample_2026_02_15_06_07.sol",
      "solcConfig": {
        "version": "0.8.20",
        "settings": {
          "evmVersion": "paris",
          "optimizer": {
            "enabled": false,
            "runs": 200
          },
          "outputSelection": {
            "*": {
              "*": [
                "abi",
                "evm.bytecode",
                "evm.deployedBytecode",
                "evm.methodIdentifiers",
                "metadata"
              ],
              "": [
                "ast"
              ]
            }
          }
        }
      },
      "imports": [],
      "versionPragmas": [
        "^0.8.20"
      ],
      "artifacts": [
        "Sample_2026_02_15_06_07"
      ]
    },
    "/home/runner/work/base-app/base-app/contracts/Sample_2026_02_15_15_56.sol": {
      "lastModificationDate": 1771170989393,
      "contentHash": "c5270f264069cb7223e913e524d1acae",
      "sourceName": "contracts/Sample_2026_02_15_15_56.sol",
      "solcConfig": {
        "version": "0.8.20",
        "settings": {
          "evmVersion": "paris",
          "optimizer": {
            "enabled": false,
            "runs": 200
          },
          "outputSelection": {
            "*": {
              "*": [
                "abi",
                "evm.bytecode",
                "evm.deployedBytecode",
                "evm.methodIdentifiers",
                "metadata"
              ],
              "": [
                "ast"
              ]
            }
          }
        }
      },
      "imports": [],
      "versionPragmas": [
        "^0.8.20"
      ],
      "artifacts": [
        "Sample_2026_02_15_15_56"
      ]
    },
    "/home/runner/work/base-app/base-app/contracts/Sample_2026_02_15_20_22.sol": {
      "lastModificationDate": 1771256381683,
      "contentHash": "218fd06b561b18ef87ba0e175e2d8e9d",
      "sourceName": "contracts/Sample_2026_02_15_20_22.sol",
      "solcConfig": {
        "version": "0.8.20",
        "settings": {
          "evmVersion": "paris",
          "optimizer": {
            "enabled": false,
            "runs": 200
          },
          "outputSelection": {
            "*": {
              "*": [
                "abi",
                "evm.bytecode",
                "evm.deployedBytecode",
                "evm.methodIdentifiers",
                "metadata"
              ],
              "": [
                "ast"
              ]
            }
          }
        }
      },
      "imports": [],
      "versionPragmas": [
        "^0.8.20"
      ],
      "artifacts": [
        "Sample_2026_02_15_20_22"
      ]
    },
    "/home/runner/work/base-app/base-app/contracts/Sample_2026_02_15_22_44.sol": {
      "lastModificationDate": 1771199184123,
      "contentHash": "3dc6a3303d5b97ceef8318e63f2bcbfb",
      "sourceName": "contracts/Sample_2026_02_15_22_44.sol",
      "solcConfig": {
        "version": "0.8.20",
        "settings": {
          "evmVersion": "paris",
          "optimizer": {
            "enabled": false,
            "runs": 200
          },
          "outputSelection": {
            "*": {
              "*": [
                "abi",
                "evm.bytecode",
                "evm.deployedBytecode",
                "evm.methodIdentifiers",
                "metadata"
              ],
              "": [
                "ast"
              ]
            }
          }
        }
      },
      "imports": [],
      "versionPragmas": [
        "^0.8.20"
      ],
      "artifacts": [
        "Sample_2026_02_15_22_44"
      ]
    },
    "/home/runner/work/base-app/base-app/contracts/Sample_2026_02_16_21_14.sol": {
      "lastModificationDate": 1771276445864,
      "contentHash": "400062014cbe927e9b9edea19ca59d19",
      "sourceName": "contracts/Sample_2026_02_16_21_14.sol",
      "solcConfig": {
        "version": "0.8.20",
        "settings": {
          "evmVersion": "paris",
          "optimizer": {
            "enabled": false,
            "runs": 200
          },
          "outputSelection": {
            "*": {
              "*": [
                "abi",
                "evm.bytecode",
                "evm.deployedBytecode",
                "evm.methodIdentifiers",
                "metadata"
              ],
              "": [
                "ast"
              ]
            }
          }
        }
      },
      "imports": [],
      "versionPragmas": [
        "^0.8.20"
      ],
      "artifacts": [
        "Sample_2026_02_16_21_14"
      ]
    }
  }
}
